cvtencode/__init__.py
cvtencode-0.0.1.dist-info/LICENSE
cvtencode-0.0.1.dist-info/METADATA
cvtencode-0.0.1.dist-info/WHEEL
cvtencode-0.0.1.dist-info/top_level.txt
cvtencode-0.0.1.dist-info/RECORD
