Metadata-Version: 2.1
Name: cvtencode
Version: 0.0.1
Summary: tiny convert encode tool, just for convenience
Home-page: https://github.com/doupongzeng/cvtencode
Author: doupongzeng
Author-email: huangzeng2016@126.com
License: UNKNOWN
Platform: UNKNOWN
Classifier: Programming Language :: Python :: 3
Classifier: License :: OSI Approved :: GNU Library or Lesser General Public License (LGPL)
Classifier: Operating System :: OS Independent
Requires-Python: >=3.6
